tbnns/__init__.py
tbnns/constants.py
tbnns/data_batcher.py
tbnns/momentum_losses.py
tbnns/nn.py
tbnns/scalar_losses.py
tbnns/tbnn.py
tbnns/tbnns.py
tbnns/utils.py
tbnns-0.5.0.dist-info/LICENSE
tbnns-0.5.0.dist-info/METADATA
tbnns-0.5.0.dist-info/WHEEL
tbnns-0.5.0.dist-info/top_level.txt
tbnns-0.5.0.dist-info/RECORD
