Metadata-Version: 2.1
Name: tbnns
Version: 0.5.0
Summary: TBNN-s - Tensor Basis Neural Network for Scalar Mixing
Home-page: https://github.com/pmmilani/tbnns.git
Author: Pedro M. Milani
Author-email: pmmilani@stanford.edu
License: Apache
Platform: UNKNOWN
Classifier: Programming Language :: Python :: 3.7
Requires-Python: >=3.6
Requires-Dist: tensorflow (==1.15.2)
Requires-Dist: joblib
